
{
    "id": 63087691,
    "name": "STARPUNK",
    "author": "Ferdefunky",
    "creators": ["Ferdefunky"],
    "verifier": "Agelio",
    "verification": "https://www.youtube.com/watch?v=bYU55AYyM6c",
    "percentToQualify": "100",
    "password": "Free to Copy",
    "records": [
         {
            "user": "Bennymccheese",
            "link": "https://www.youtube.com/watch?v=UgRHBAi4xVg",
            "percent": 100,
            "hz": 69
        },
        {
            "user": "bastion2000.",
            "link": "https://www.youtube.com/watch?v=UgRHBAi4xVg",
            "percent": 100,
            "hz": 69
        }
    ]
}
